pygame_helper_lib/__init__.py
pygame_helper_lib/colors.py
pygame_helper_lib/debuginfo.py
pygame_helper_lib/game.py
pygame_helper_lib/object.py
pygame_helper_lib/saveload.py
pygame_helper_lib/scene.py
pygame_helper_lib/tilemaploader.py
pygame_helper_lib-1.2.0.dist-info/WHEEL
pygame_helper_lib-1.2.0.dist-info/METADATA
pygame_helper_lib-1.2.0.dist-info/RECORD
