Metadata-Version: 2.1
Name: pygame-helper-lib
Version: 1.2.0
Summary: A helper library for pygame
Author: VL07
Requires-Python: >=3.7
Classifier: License :: OSI Approved :: MIT License
Classifier: Operating System :: OS Independent
Classifier: Programming Language :: Python :: 3
Project-URL: Bug Tracker, https://github.com/VL07/pygameHelperLib/issues
Project-URL: Homepage, https://github.com/VL07/pygameHelperLib
